stchess/__init__.py
stchess/config.py
stchess-0.0.1.dist-info/LICENSE
stchess-0.0.1.dist-info/METADATA
stchess-0.0.1.dist-info/WHEEL
stchess-0.0.1.dist-info/top_level.txt
stchess-0.0.1.dist-info/RECORD
